Metadata-Version: 2.4
Name: mseep-mcp-server-sqlexpress
Version: 0.1.4
Summary: A Microsoft SQL Server (SQLEXPRESS) MCP server
Author-email: mseep <support@skydeck.ai>
License-File: LICENSE
Requires-Python: >=3.10
Requires-Dist: mcp>=1.0.0
Requires-Dist: pyodbc>=5.0.0
